README.txt
setup.py
collective/__init__.py
collective.twitterportlet.egg-info/PKG-INFO
collective.twitterportlet.egg-info/SOURCES.txt
collective.twitterportlet.egg-info/dependency_links.txt
collective.twitterportlet.egg-info/entry_points.txt
collective.twitterportlet.egg-info/namespace_packages.txt
collective.twitterportlet.egg-info/not-zip-safe
collective.twitterportlet.egg-info/requires.txt
collective.twitterportlet.egg-info/top_level.txt
collective/twitterportlet/README.txt
collective/twitterportlet/__init__.py
collective/twitterportlet/configure.zcml
collective/twitterportlet/portlet.pt
collective/twitterportlet/portlet.py
collective/twitterportlet/tests.py
collective/twitterportlet/version.txt
collective/twitterportlet/profiles/default/metadata.xml
collective/twitterportlet/profiles/default/portlets.xml
docs/HISTORY.txt
docs/INSTALL.txt
docs/LICENSE.GPL
docs/LICENSE.txt