Metadata-Version: 1.0
Name: collective.twitterportlet
Version: 0.5
Summary: A Twitter portlet for Plone.
Home-page: http://sharkbyte.co.uk
Author: Sharkbyte Studios
Author-email: support@sharkbyte.co.uk
License: GPL
Platform: UNKNOWN
Classifier: Framework :: Plone
Classifier: Programming Language :: Python
Classifier: Topic :: Software Development :: Libraries :: Python Modules
